oscarsturtle/__init__.py
oscarsturtle/__main__.py
oscarsturtle-0.0.3.dist-info/METADATA
oscarsturtle-0.0.3.dist-info/WHEEL
oscarsturtle-0.0.3.dist-info/RECORD
